discord/ext/better_options_description/__init__.py
discord_ext_better_options_description-1.0.dist-info/LICENSE
discord_ext_better_options_description-1.0.dist-info/METADATA
discord_ext_better_options_description-1.0.dist-info/WHEEL
discord_ext_better_options_description-1.0.dist-info/dependency_links.txt
discord_ext_better_options_description-1.0.dist-info/top_level.txt
discord_ext_better_options_description-1.0.dist-info/RECORD
