Metadata-Version: 2.1
Name: discord-ext-better-options-description
Version: 1.0
Summary: Discord.py extension to keep your slash commands options neat and tidy.
Home-page: https://github.com/Nohet/discord-ext-better-options-description
Author: Nohet
Author-email: igorczupryniak503@gmail.com
License: MIT
Keywords: discord,discord extension,discord.py,slashcommands
Classifier: Development Status :: 5 - Production/Stable
Classifier: Intended Audience :: Developers
Classifier: License :: OSI Approved :: MIT License
Classifier: Programming Language :: Python :: 3
License-File: LICENSE
Requires-Dist: discord.py
Requires-Dist: PyYAML
